<annotation>
	<folder></folder>
	<filename>4_jpeg.rf.3a97c016d7aef4d5449e52a63418c498.jpg</filename>
	<path>4_jpeg.rf.3a97c016d7aef4d5449e52a63418c498.jpg</path>
	<source>
		<database>roboflow.com</database>
	</source>
	<size>
		<width>640</width>
		<height>640</height>
		<depth>3</depth>
	</size>
	<segmented>0</segmented>
	<object>
		<name>image</name>
		<pose>Unspecified</pose>
		<truncated>0</truncated>
		<difficult>0</difficult>
		<occluded>0</occluded>
		<bndbox>
			<xmin>85</xmin>
			<xmax>266</xmax>
			<ymin>1</ymin>
			<ymax>50</ymax>
		</bndbox>
	</object>
	<object>
		<name>image</name>
		<pose>Unspecified</pose>
		<truncated>0</truncated>
		<difficult>0</difficult>
		<occluded>0</occluded>
		<bndbox>
			<xmin>121</xmin>
			<xmax>199</xmax>
			<ymin>60</ymin>
			<ymax>118</ymax>
		</bndbox>
	</object>
	<object>
		<name>image</name>
		<pose>Unspecified</pose>
		<truncated>0</truncated>
		<difficult>0</difficult>
		<occluded>0</occluded>
		<bndbox>
			<xmin>105</xmin>
			<xmax>204</xmax>
			<ymin>126</ymin>
			<ymax>185</ymax>
		</bndbox>
	</object>
	<object>
		<name>image</name>
		<pose>Unspecified</pose>
		<truncated>0</truncated>
		<difficult>0</difficult>
		<occluded>0</occluded>
		<bndbox>
			<xmin>403</xmin>
			<xmax>476</xmax>
			<ymin>81</ymin>
			<ymax>139</ymax>
		</bndbox>
	</object>
	<object>
		<name>image</name>
		<pose>Unspecified</pose>
		<truncated>0</truncated>
		<difficult>0</difficult>
		<occluded>0</occluded>
		<bndbox>
			<xmin>381</xmin>
			<xmax>468</xmax>
			<ymin>151</ymin>
			<ymax>213</ymax>
		</bndbox>
	</object>
	<object>
		<name>label</name>
		<pose>Unspecified</pose>
		<truncated>0</truncated>
		<difficult>0</difficult>
		<occluded>0</occluded>
		<bndbox>
			<xmin>250</xmin>
			<xmax>327</xmax>
			<ymin>81</ymin>
			<ymax>114</ymax>
		</bndbox>
	</object>
	<object>
		<name>label</name>
		<pose>Unspecified</pose>
		<truncated>0</truncated>
		<difficult>0</difficult>
		<occluded>0</occluded>
		<bndbox>
			<xmin>500</xmin>
			<xmax>568</xmax>
			<ymin>104</ymin>
			<ymax>127</ymax>
		</bndbox>
	</object>
	<object>
		<name>label</name>
		<pose>Unspecified</pose>
		<truncated>0</truncated>
		<difficult>0</difficult>
		<occluded>0</occluded>
		<bndbox>
			<xmin>256</xmin>
			<xmax>341</xmax>
			<ymin>151</ymin>
			<ymax>184</ymax>
		</bndbox>
	</object>
	<object>
		<name>label</name>
		<pose>Unspecified</pose>
		<truncated>0</truncated>
		<difficult>0</difficult>
		<occluded>0</occluded>
		<bndbox>
			<xmin>487</xmin>
			<xmax>565</xmax>
			<ymin>173</ymin>
			<ymax>199</ymax>
		</bndbox>
	</object>
	<object>
		<name>button</name>
		<pose>Unspecified</pose>
		<truncated>0</truncated>
		<difficult>0</difficult>
		<occluded>0</occluded>
		<bndbox>
			<xmin>211</xmin>
			<xmax>394</xmax>
			<ymin>202</ymin>
			<ymax>254</ymax>
		</bndbox>
	</object>
	<object>
		<name>button</name>
		<pose>Unspecified</pose>
		<truncated>0</truncated>
		<difficult>0</difficult>
		<occluded>0</occluded>
		<bndbox>
			<xmin>488</xmin>
			<xmax>630</xmax>
			<ymin>221</ymin>
			<ymax>274</ymax>
		</bndbox>
	</object>
</annotation>
