<annotation>
	<folder></folder>
	<filename>PXL_20230408_090057069_jpg.rf.a791d4651588c8f5f1c1101b8f88238a.jpg</filename>
	<path>PXL_20230408_090057069_jpg.rf.a791d4651588c8f5f1c1101b8f88238a.jpg</path>
	<source>
		<database>roboflow.com</database>
	</source>
	<size>
		<width>640</width>
		<height>640</height>
		<depth>3</depth>
	</size>
	<segmented>0</segmented>
	<object>
		<name>button</name>
		<pose>Unspecified</pose>
		<truncated>0</truncated>
		<difficult>0</difficult>
		<occluded>0</occluded>
		<bndbox>
			<xmin>31</xmin>
			<xmax>191</xmax>
			<ymin>91</ymin>
			<ymax>145</ymax>
		</bndbox>
	</object>
	<object>
		<name>button</name>
		<pose>Unspecified</pose>
		<truncated>0</truncated>
		<difficult>0</difficult>
		<occluded>0</occluded>
		<bndbox>
			<xmin>202</xmin>
			<xmax>344</xmax>
			<ymin>93</ymin>
			<ymax>141</ymax>
		</bndbox>
	</object>
	<object>
		<name>textarea</name>
		<pose>Unspecified</pose>
		<truncated>0</truncated>
		<difficult>0</difficult>
		<occluded>0</occluded>
		<bndbox>
			<xmin>28</xmin>
			<xmax>186</xmax>
			<ymin>192</ymin>
			<ymax>280</ymax>
		</bndbox>
	</object>
	<object>
		<name>checkbox</name>
		<pose>Unspecified</pose>
		<truncated>0</truncated>
		<difficult>0</difficult>
		<occluded>0</occluded>
		<bndbox>
			<xmin>33</xmin>
			<xmax>184</xmax>
			<ymin>338</ymin>
			<ymax>375</ymax>
		</bndbox>
	</object>
	<object>
		<name>input</name>
		<pose>Unspecified</pose>
		<truncated>0</truncated>
		<difficult>0</difficult>
		<occluded>0</occluded>
		<bndbox>
			<xmin>425</xmin>
			<xmax>546</xmax>
			<ymin>98</ymin>
			<ymax>134</ymax>
		</bndbox>
	</object>
	<object>
		<name>toggle</name>
		<pose>Unspecified</pose>
		<truncated>0</truncated>
		<difficult>0</difficult>
		<occluded>0</occluded>
		<bndbox>
			<xmin>425</xmin>
			<xmax>473</xmax>
			<ymin>191</ymin>
			<ymax>221</ymax>
		</bndbox>
	</object>
	<object>
		<name>toggle</name>
		<pose>Unspecified</pose>
		<truncated>0</truncated>
		<difficult>0</difficult>
		<occluded>0</occluded>
		<bndbox>
			<xmin>514</xmin>
			<xmax>557</xmax>
			<ymin>190</ymin>
			<ymax>221</ymax>
		</bndbox>
	</object>
	<object>
		<name>image</name>
		<pose>Unspecified</pose>
		<truncated>0</truncated>
		<difficult>0</difficult>
		<occluded>0</occluded>
		<bndbox>
			<xmin>523</xmin>
			<xmax>561</xmax>
			<ymin>293</ymin>
			<ymax>343</ymax>
		</bndbox>
	</object>
	<object>
		<name>image</name>
		<pose>Unspecified</pose>
		<truncated>0</truncated>
		<difficult>0</difficult>
		<occluded>0</occluded>
		<bndbox>
			<xmin>416</xmin>
			<xmax>472</xmax>
			<ymin>306</ymin>
			<ymax>362</ymax>
		</bndbox>
	</object>
</annotation>
