<annotation>
	<folder></folder>
	<filename>PXL_20230415_195935082_jpg.rf.6ef3ca4a5aba39ba4098a03065f8c7b5.jpg</filename>
	<path>PXL_20230415_195935082_jpg.rf.6ef3ca4a5aba39ba4098a03065f8c7b5.jpg</path>
	<source>
		<database>roboflow.com</database>
	</source>
	<size>
		<width>640</width>
		<height>640</height>
		<depth>3</depth>
	</size>
	<segmented>0</segmented>
	<object>
		<name>image</name>
		<pose>Unspecified</pose>
		<truncated>0</truncated>
		<difficult>0</difficult>
		<occluded>0</occluded>
		<bndbox>
			<xmin>443</xmin>
			<xmax>641</xmax>
			<ymin>158</ymin>
			<ymax>444</ymax>
		</bndbox>
	</object>
	<object>
		<name>container</name>
		<pose>Unspecified</pose>
		<truncated>0</truncated>
		<difficult>0</difficult>
		<occluded>0</occluded>
		<bndbox>
			<xmin>3</xmin>
			<xmax>445</xmax>
			<ymin>121</ymin>
			<ymax>500</ymax>
		</bndbox>
	</object>
	<object>
		<name>button</name>
		<pose>Unspecified</pose>
		<truncated>0</truncated>
		<difficult>0</difficult>
		<occluded>0</occluded>
		<bndbox>
			<xmin>20</xmin>
			<xmax>150</xmax>
			<ymin>197</ymin>
			<ymax>295</ymax>
		</bndbox>
	</object>
	<object>
		<name>button</name>
		<pose>Unspecified</pose>
		<truncated>0</truncated>
		<difficult>0</difficult>
		<occluded>0</occluded>
		<bndbox>
			<xmin>189</xmin>
			<xmax>375</xmax>
			<ymin>176</ymin>
			<ymax>274</ymax>
		</bndbox>
	</object>
	<object>
		<name>table</name>
		<pose>Unspecified</pose>
		<truncated>0</truncated>
		<difficult>0</difficult>
		<occluded>0</occluded>
		<bndbox>
			<xmin>40</xmin>
			<xmax>358</xmax>
			<ymin>289</ymin>
			<ymax>460</ymax>
		</bndbox>
	</object>
</annotation>
